cdcmis.cpython-36m-x86_64-linux-gnu.so
cdcmis-0.1.3.dist-info/DESCRIPTION.rst
cdcmis-0.1.3.dist-info/metadata.json
cdcmis-0.1.3.dist-info/top_level.txt
cdcmis-0.1.3.dist-info/WHEEL
cdcmis-0.1.3.dist-info/METADATA
cdcmis-0.1.3.dist-info/RECORD
