Metadata-Version: 2.1
Name: cdcmis
Version: 0.1.3
Summary: cdcmis
Home-page: UNKNOWN
Author: Danian Hu
Author-email: hudanian@gmail.com
License: UNKNOWN
Platform: UNKNOWN
